{
    "0xfa2": {
        "gtmn": "0x8C7A8d4058F5585e32Dd4Cef4581284c612B90Db",
        "deploy": 13983516,
        "rpc": "https://rpc.ankr.com/fantom_testnet"
    },
    "0x61": {
        "gtmn": "0x8C7A8d4058F5585e32Dd4Cef4581284c612B90Db",
        "deploy": 27336602,
        "rpc": "https://rpc.ankr.com/bsc_testnet_chapel"
    },
    "0xaa36a7": {
        "gtmn": "0x8C7A8d4058F5585e32Dd4Cef4581284c612B90Db",
        "deploy": 2923977,
        "rpc": "https://rpc.ankr.com/eth_sepolia"
    },
    "0xa869": {
        "gtmn": "0x8C7A8d4058F5585e32Dd4Cef4581284c612B90Db",
        "deploy": 19038266,
        "rpc": "https://rpc.ankr.com/avalanche_fuji"
    }
}